test/byte_sus_tester.v
// Tester modules for Byte Striping & Un-striping

// Tester module for Byte Striping
module TESTER_STRIPING(lane_0, lane_1, valid_0, valid_1, data_in, valid_in, clk_2f, clk_f);
	input [31:0] lane_0, lane_1;
	input valid_0, valid_1;
	output reg [31:0] data_in;
	output reg valid_in, clk_2f, clk_f;

	initial begin
		$dumpfile("byte_sus.vcd");
		$dumpvars;
		// Initialize inputs
		data_in = 'b0;
		valid_in = 1;
		
		#3
		repeat (4)
			begin
				@(posedge clk_2f)
					data_in <= 32'hFFFF_FFFF;
				@(posedge clk_2f)
					data_in <= 32'hEEEE_EEEE;
				@(posedge clk_2f)
					data_in <= 32'hDDDD_DDDD;
				@(posedge clk_2f)
					data_in <= 32'hCCCC_CCCC;
			end
		$finish;
	end
	
	initial clk_2f <= 0;
	always #8 clk_2f <= ~clk_2f;
	initial clk_f <= 0;
	always @(posedge clk_2f) clk_f <= ~clk_f;
endmodule


// Tester module for Byte Un-striping
module TESTER_UNSTRIPING(lane_0, lane_1, valid_0, valid_1, data_out, valid_out, clk_2f, clk_f);
	output reg [31:0] lane_0, lane_1;
	output reg valid_0, valid_1;
	input [31:0] data_out;
	input valid_out;
	output reg clk_2f, clk_f;

	initial begin
		// Initialize inputs
		{lane_0, lane_1} = 'b0;
		{valid_0, valid_1} = 2'b11;
		
		#3
		repeat (8)
			begin
				@(posedge clk_f)
					lane_0 <= 32'hFFFF_FFFF;
					lane_1 <= 32'hEEEE_EEEE;
				@(posedge clk_f)
					lane_0 <= 32'hDDDD_DDDD;
					lane_1 <= 32'hCCCC_CCCC;
			end
	end
	
	initial clk_2f <= 0;
	always #8 clk_2f <= ~clk_2f;
	initial clk_f <= 0;
	always @(posedge clk_2f) clk_f <= ~clk_f;
endmodule

src/byte_sus.v
/* PHY Layer for PCIe Interface
 * Byte striping & un-striping modules
 * Created: September 30, 2021
 *
 */
// Byte Striping
module BYTE_STRIPING(lane_0, lane_1, valid_0, valid_1, data_in, valid_in, clk_2f, clk_f);
	output reg [31:0] lane_0, lane_1;
	output reg valid_0, valid_1;
	input [31:0] data_in;
	input valid_in, clk_2f, clk_f;
	always
		begin
		
			@(posedge clk_2f)
				#0.5
				if(valid_in == 1)
					begin
						lane_0 <= data_in;
						valid_0 <= valid_in;
					end
			
			@(posedge clk_2f)
				#0.5
				if(valid_in == 1)
					begin
						lane_1 <= data_in;
						valid_1 <= valid_in;
					end
		end
endmodule


// Byte Un-Striping
module BYTE_UNSTRIPING(data_out, valid_out, lane_0, lane_1, valid_0, valid_1, clk_2f, clk_f);
	output reg [31:0] data_out;
	output reg valid_out;
	input [31:0] lane_0, lane_1;
	input valid_0, valid_1, clk_2f, clk_f;
	always
		begin
			@(posedge clk_2f)
				#0.5
				if(valid_0 == 1)
					begin
						data_out <= lane_0;
						valid_out <= valid_0;
					end
			@(posedge clk_2f)
				#0.5
				if(valid_0 == 1)
					begin
						data_out <= lane_1;
						valid_out <= valid_1;
					end
		end

endmodule

test/byte_sus_testbench.v
`timescale 1ns / 1ns

// Testbench modules for Byte Striping & Un-striping
`include "byte_sus_tester.v"
`include "../src/byte_sus.v"

module TESTBENCH_STRIPING;
	wire [31:0] lane_0, lane_1;
	wire valid_0, valid_1;
	wire [31:0] data_in;
	wire valid_in, clk_f, clk_2f;


BYTE_STRIPING mstriping(.lane_0			(lane_0),
						.lane_1			(lane_1),
						.valid_0		(valid_0),
						.valid_1		(valid_1),
						.data_in		(data_in),
						.valid_in		(valid_in),
						.clk_2f			(clk_2f),
						.clk_f			(clk_f)
						);

TESTER_STRIPING mtester(.lane_0			(lane_0),
						.lane_1			(lane_1),
						.valid_0		(valid_0),
						.valid_1		(valid_1),
						.data_in		(data_in),
						.valid_in		(valid_in),
						.clk_2f			(clk_2f),
						.clk_f			(clk_f)
						);

endmodule

module TESTBENCH_UNSTRIPING;
	wire [31:0] lane_0, lane_1;
	wire valid_0, valid_1;
	wire [31:0] data_out;
	wire valid_out, clk_f, clk_2f;


BYTE_UNSTRIPING munstriping(.lane_0			(lane_0),
							.lane_1			(lane_1),
							.valid_0		(valid_0),
							.valid_1		(valid_1),
							.data_out		(data_out),
							.valid_out		(valid_out),
							.clk_2f			(clk_2f),
							.clk_f			(clk_f)
							);

TESTER_UNSTRIPING mtester(.lane_0			(lane_0),
							.lane_1			(lane_1),
							.valid_0		(valid_0),
							.valid_1		(valid_1),
							.data_out		(data_out),
							.valid_out		(valid_out),
							.clk_2f			(clk_2f),
							.clk_f			(clk_f)
							);

endmodule

test/byte_sus.vcd
$date
	Fri Oct  1 21:00:31 2021
$end
$version
	Icarus Verilog
$end
$timescale
	1ns
$end
$scope module TESTBENCH_STRIPING $end
$var wire 1 ! valid_in $end
$var wire 1 " valid_1 $end
$var wire 1 # valid_0 $end
$var wire 32 $ lane_1 [31:0] $end
$var wire 32 % lane_0 [31:0] $end
$var wire 32 & data_in [31:0] $end
$var wire 1 ' clk_f $end
$var wire 1 ( clk_2f $end
$scope module mstriping $end
$var wire 1 ! valid_in $end
$var wire 32 ) data_in [31:0] $end
$var wire 1 ' clk_f $end
$var wire 1 ( clk_2f $end
$var reg 32 * lane_0 [31:0] $end
$var reg 32 + lane_1 [31:0] $end
$var reg 1 # valid_0 $end
$var reg 1 " valid_1 $end
$upscope $end
$scope module mtester $end
$var wire 32 , lane_0 [31:0] $end
$var wire 32 - lane_1 [31:0] $end
$var wire 1 # valid_0 $end
$var wire 1 " valid_1 $end
$var reg 1 ( clk_2f $end
$var reg 1 ' clk_f $end
$var reg 32 . data_in [31:0] $end
$var reg 1 ! valid_in $end
$upscope $end
$upscope $end
$scope module TESTBENCH_UNSTRIPING $end
$var wire 1 / valid_out $end
$var wire 1 0 valid_1 $end
$var wire 1 1 valid_0 $end
$var wire 32 2 lane_1 [31:0] $end
$var wire 32 3 lane_0 [31:0] $end
$var wire 32 4 data_out [31:0] $end
$var wire 1 5 clk_f $end
$var wire 1 6 clk_2f $end
$scope module mtester $end
$var wire 1 / valid_out $end
$var wire 32 7 data_out [31:0] $end
$var reg 1 6 clk_2f $end
$var reg 1 5 clk_f $end
$var reg 32 8 lane_0 [31:0] $end
$var reg 32 9 lane_1 [31:0] $end
$var reg 1 1 valid_0 $end
$var reg 1 0 valid_1 $end
$upscope $end
$scope module munstriping $end
$var wire 1 6 clk_2f $end
$var wire 1 5 clk_f $end
$var wire 32 : lane_0 [31:0] $end
$var wire 32 ; lane_1 [31:0] $end
$var wire 1 1 valid_0 $end
$var wire 1 0 valid_1 $end
$var reg 32 < data_out [31:0] $end
$var reg 1 / valid_out $end
$upscope $end
$upscope $end
$enddefinitions $end
#0
$dumpvars
bx <
b0 ;
b0 :
b0 9
b0 8
bx 7
06
05
bx 4
b0 3
b0 2
11
10
x/
b0 .
bx -
bx ,
bx +
bx *
b0 )
0(
0'
b0 &
bx %
bx $
x#
x"
1!
$end
#8
b11101110111011101110111011101110 2
b11101110111011101110111011101110 9
b11101110111011101110111011101110 ;
b11111111111111111111111111111111 3
b11111111111111111111111111111111 8
b11111111111111111111111111111111 :
15
1'
b11111111111111111111111111111111 &
b11111111111111111111111111111111 )
b11111111111111111111111111111111 .
16
1(
#9
1/
b11111111111111111111111111111111 4
b11111111111111111111111111111111 7
b11111111111111111111111111111111 <
1#
b11111111111111111111111111111111 %
b11111111111111111111111111111111 *
b11111111111111111111111111111111 ,
#16
06
0(
#24
05
b11101110111011101110111011101110 &
b11101110111011101110111011101110 )
b11101110111011101110111011101110 .
0'
16
1(
#25
b11101110111011101110111011101110 4
b11101110111011101110111011101110 7
b11101110111011101110111011101110 <
1"
b11101110111011101110111011101110 $
b11101110111011101110111011101110 +
b11101110111011101110111011101110 -
#32
06
0(
#40
b11001100110011001100110011001100 2
b11001100110011001100110011001100 9
b11001100110011001100110011001100 ;
b11011101110111011101110111011101 3
b11011101110111011101110111011101 8
b11011101110111011101110111011101 :
15
1'
b11011101110111011101110111011101 &
b11011101110111011101110111011101 )
b11011101110111011101110111011101 .
16
1(
#41
b11011101110111011101110111011101 4
b11011101110111011101110111011101 7
b11011101110111011101110111011101 <
b11011101110111011101110111011101 %
b11011101110111011101110111011101 *
b11011101110111011101110111011101 ,
#48
06
0(
#56
05
b11001100110011001100110011001100 &
b11001100110011001100110011001100 )
b11001100110011001100110011001100 .
0'
16
1(
#57
b11001100110011001100110011001100 4
b11001100110011001100110011001100 7
b11001100110011001100110011001100 <
b11001100110011001100110011001100 $
b11001100110011001100110011001100 +
b11001100110011001100110011001100 -
#64
06
0(
#72
b11101110111011101110111011101110 2
b11101110111011101110111011101110 9
b11101110111011101110111011101110 ;
b11111111111111111111111111111111 3
b11111111111111111111111111111111 8
b11111111111111111111111111111111 :
15
1'
b11111111111111111111111111111111 &
b11111111111111111111111111111111 )
b11111111111111111111111111111111 .
16
1(
#73
b11111111111111111111111111111111 4
b11111111111111111111111111111111 7
b11111111111111111111111111111111 <
b11111111111111111111111111111111 %
b11111111111111111111111111111111 *
b11111111111111111111111111111111 ,
#80
06
0(
#88
05
b11101110111011101110111011101110 &
b11101110111011101110111011101110 )
b11101110111011101110111011101110 .
0'
16
1(
#89
b11101110111011101110111011101110 4
b11101110111011101110111011101110 7
b11101110111011101110111011101110 <
b11101110111011101110111011101110 $
b11101110111011101110111011101110 +
b11101110111011101110111011101110 -
#96
06
0(
#104
b11001100110011001100110011001100 2
b11001100110011001100110011001100 9
b11001100110011001100110011001100 ;
b11011101110111011101110111011101 3
b11011101110111011101110111011101 8
b11011101110111011101110111011101 :
15
1'
b11011101110111011101110111011101 &
b11011101110111011101110111011101 )
b11011101110111011101110111011101 .
16
1(
#105
b11011101110111011101110111011101 4
b11011101110111011101110111011101 7
b11011101110111011101110111011101 <
b11011101110111011101110111011101 %
b11011101110111011101110111011101 *
b11011101110111011101110111011101 ,
#112
06
0(
#120
05
b11001100110011001100110011001100 &
b11001100110011001100110011001100 )
b11001100110011001100110011001100 .
0'
16
1(
#121
b11001100110011001100110011001100 4
b11001100110011001100110011001100 7
b11001100110011001100110011001100 <
b11001100110011001100110011001100 $
b11001100110011001100110011001100 +
b11001100110011001100110011001100 -
#128
06
0(
#136
b11101110111011101110111011101110 2
b11101110111011101110111011101110 9
b11101110111011101110111011101110 ;
b11111111111111111111111111111111 3
b11111111111111111111111111111111 8
b11111111111111111111111111111111 :
15
1'
b11111111111111111111111111111111 &
b11111111111111111111111111111111 )
b11111111111111111111111111111111 .
16
1(
#137
b11111111111111111111111111111111 4
b11111111111111111111111111111111 7
b11111111111111111111111111111111 <
b11111111111111111111111111111111 %
b11111111111111111111111111111111 *
b11111111111111111111111111111111 ,
#144
06
0(
#152
05
b11101110111011101110111011101110 &
b11101110111011101110111011101110 )
b11101110111011101110111011101110 .
0'
16
1(
#153
b11101110111011101110111011101110 4
b11101110111011101110111011101110 7
b11101110111011101110111011101110 <
b11101110111011101110111011101110 $
b11101110111011101110111011101110 +
b11101110111011101110111011101110 -
#160
06
0(
#168
b11001100110011001100110011001100 2
b11001100110011001100110011001100 9
b11001100110011001100110011001100 ;
b11011101110111011101110111011101 3
b11011101110111011101110111011101 8
b11011101110111011101110111011101 :
15
1'
b11011101110111011101110111011101 &
b11011101110111011101110111011101 )
b11011101110111011101110111011101 .
16
1(
#169
b11011101110111011101110111011101 4
b11011101110111011101110111011101 7
b11011101110111011101110111011101 <
b11011101110111011101110111011101 %
b11011101110111011101110111011101 *
b11011101110111011101110111011101 ,
#176
06
0(
#184
05
b11001100110011001100110011001100 &
b11001100110011001100110011001100 )
b11001100110011001100110011001100 .
0'
16
1(
#185
b11001100110011001100110011001100 4
b11001100110011001100110011001100 7
b11001100110011001100110011001100 <
b11001100110011001100110011001100 $
b11001100110011001100110011001100 +
b11001100110011001100110011001100 -
#192
06
0(
#200
b11101110111011101110111011101110 2
b11101110111011101110111011101110 9
b11101110111011101110111011101110 ;
b11111111111111111111111111111111 3
b11111111111111111111111111111111 8
b11111111111111111111111111111111 :
15
1'
b11111111111111111111111111111111 &
b11111111111111111111111111111111 )
b11111111111111111111111111111111 .
16
1(
#201
b11111111111111111111111111111111 4
b11111111111111111111111111111111 7
b11111111111111111111111111111111 <
b11111111111111111111111111111111 %
b11111111111111111111111111111111 *
b11111111111111111111111111111111 ,
#208
06
0(
#216
05
b11101110111011101110111011101110 &
b11101110111011101110111011101110 )
b11101110111011101110111011101110 .
0'
16
1(
#217
b11101110111011101110111011101110 4
b11101110111011101110111011101110 7
b11101110111011101110111011101110 <
b11101110111011101110111011101110 $
b11101110111011101110111011101110 +
b11101110111011101110111011101110 -
#224
06
0(
#232
b11001100110011001100110011001100 2
b11001100110011001100110011001100 9
b11001100110011001100110011001100 ;
b11011101110111011101110111011101 3
b11011101110111011101110111011101 8
b11011101110111011101110111011101 :
15
1'
b11011101110111011101110111011101 &
b11011101110111011101110111011101 )
b11011101110111011101110111011101 .
16
1(
#233
b11011101110111011101110111011101 4
b11011101110111011101110111011101 7
b11011101110111011101110111011101 <
b11011101110111011101110111011101 %
b11011101110111011101110111011101 *
b11011101110111011101110111011101 ,
#240
06
0(
#248
05
b11001100110011001100110011001100 &
b11001100110011001100110011001100 )
b11001100110011001100110011001100 .
0'
16
1(
